swc/__init__.py
swc/__main__.py
swc/__version__.py
swc/cli.py
swc/context.py
swc/datetime_converter.py
swc/libssc.dylib
swc/libssc.so
swc/log.py
swc/nsrdb.py
swc/nsrdb_cli.py
swc/sam.py
swc/sam_simulation.py
swc/sam_simulation_cli.py
swc/solar.py
swc/ssc.dll
swc/ssc.dylib
swc/sscapi.py
swc/utils.py
swc-0.7.2.data/data/compilers/libssc.dylib
swc-0.7.2.data/data/compilers/libssc.so
swc-0.7.2.data/data/compilers/ssc.dll
swc-0.7.2.dist-info/LICENSE.txt
swc-0.7.2.dist-info/METADATA
swc-0.7.2.dist-info/WHEEL
swc-0.7.2.dist-info/top_level.txt
swc-0.7.2.dist-info/RECORD
