Metadata-Version: 2.1
Name: swc
Version: 0.7.2
Summary: Solar performance calculator
Home-page: https://github.com/pesap/swc
Author: P. A. Sanchez-Perez
Author-email: pesapsanchez@gmal.com
License: UNKNOWN
Project-URL: Bug Tracker, https://github.com/pesap/swc/issues
Platform: UNKNOWN
Classifier: Programming Language :: Python :: 3
Classifier: License :: OSI Approved :: MIT License
Classifier: Operating System :: OS Independent
License-File: LICENSE.txt
Requires-Dist: pandas
Requires-Dist: requests
Requires-Dist: tqdm
Requires-Dist: click
Requires-Dist: python-dotenv
Provides-Extra: dev
Requires-Dist: twine ; extra == 'dev'
Requires-Dist: ipython ; extra == 'dev'
Requires-Dist: bump2version ; extra == 'dev'
